feriados_brasileiros/__init__.py
feriados_brasileiros/datas.py
feriados_brasileiros-0.0.8.dist-info/LICENSE
feriados_brasileiros-0.0.8.dist-info/METADATA
feriados_brasileiros-0.0.8.dist-info/WHEEL
feriados_brasileiros-0.0.8.dist-info/top_level.txt
feriados_brasileiros-0.0.8.dist-info/RECORD
