Metadata-Version: 2.1
Name: feriados-brasileiros
Version: 0.0.8
Summary: Feriados Brasileiros
Home-page: https://github.com/michelmetran/feriados
Author: Michel Metran
Author-email: michelmetran@gmail.com
Keywords: python,datas,feriados
Classifier: Programming Language :: Python :: 3
Classifier: License :: OSI Approved :: MIT License
Classifier: Operating System :: OS Independent
Classifier: Natural Language :: Portuguese
Classifier: Intended Audience :: Developers
Requires-Python: >=3
License-File: LICENSE
Requires-Dist: pandas
Requires-Dist: numpy
